Metadata-Version: 2.1
Name: ibis-mssql
Version: 0.1.5
Summary: Ibis backend for MSSQL
Home-page: https://github.com/quansight/ibis-mssql
Maintainer: Quansight
Maintainer-email: costrouchov@quansight.com
License: Apache License, Version 2.0
Platform: UNKNOWN
Classifier: Development Status :: 4 - Beta
Classifier: Operating System :: OS Independent
Classifier: Intended Audience :: Science/Research
Classifier: Programming Language :: Python
Classifier: Programming Language :: Python :: 3
Classifier: Topic :: Scientific/Engineering
Requires-Python: >=3.7,<3.9
Provides-Extra: develop
